[
    {
        "group": "TBA",
        "sku": "ACC-HYTE-GWING-WS",
        "description": null,
        "eta": null,
        "communicated_date": "Q4 2025",
        "quantity": 0
    },
    {
        "group": "Out of Stocks",
        "sku": "ACC-HYTE-LS10-B-3NP",
        "description": null,
        "eta": null,
        "communicated_date": null,
        "quantity": 0
    },
    {
        "group": "Out of Stocks",
        "sku": "ACC-HYTE-P3R-KEYCAP",
        "description": null,
        "eta": null,
        "communicated_date": null,
        "quantity": 0
    },
    {
        "group": "Out of Stocks",
        "sku": "ACC-HYTE-P3R-KEYCAP-B",
        "description": null,
        "eta": null,
        "communicated_date": null,
        "quantity": 0
    },
    {
        "group": "Out of Stocks",
        "sku": "ACC-HYTE-PCIE50-BR",
        "description": "[BLACK CHERRY] HYTE PCIE50 HYPER RISER",
        "eta": null,
        "communicated_date": null,
        "quantity": 100
    },
    {
        "group": "Out of Stocks",
        "sku": "ACC-HYTE-PCIE50-MM",
        "description": "[MATCHA MILK] HYTE PCIE50 HYPER RISER",
        "eta": null,
        "communicated_date": null,
        "quantity": 100
    },
    {
        "group": "Out of Stocks",
        "sku": "ACC-HYTE-PCIE50-WW",
        "description": "[SNOW WHITE] HYTE PCIE50 HYPER RISER",
        "eta": null,
        "communicated_date": null,
        "quantity": 200
    },
    {
        "group": "Out of Stocks",
        "sku": "ACC-HYTE-SPF-1851-BB",
        "description": "[PITCH BLACK] HYTE SOLID PROCESSOR FRAME \u2013 SOCKET 1851",
        "eta": "2025-09-12",
        "communicated_date": null,
        "quantity": 220
    },
    {
        "group": "Out of Stocks",
        "sku": "ACC-HYTE-SPF-1851-WW",
        "description": "[SNOW WHITE] HYTE SOLID PROCESSOR FRAME \u2013 SOCKET 1851",
        "eta": "2025-09-12",
        "communicated_date": null,
        "quantity": 220
    },
    {
        "group": "Out of Stocks",
        "sku": "ACC-HYTE-SPF-AM5-RR",
        "description": "[CHERRY] HYTE SOLID PROCESSOR FRAME \u2013 SOCKET AM5",
        "eta": "2025-09-12",
        "communicated_date": null,
        "quantity": 220
    },
    {
        "group": "Out of Stocks",
        "sku": "ACC-HYTE-SPF-AM5-WW",
        "description": "[SNOW WHITE] HYTE SOLID PROCESSOR FRAME \u2013 SOCKET AM5",
        "eta": "2025-09-12",
        "communicated_date": null,
        "quantity": 80
    },
    {
        "group": "Out of Stocks",
        "sku": "CS-HYTE-DOKI-Y70",
        "description": null,
        "eta": null,
        "communicated_date": null,
        "quantity": 0
    },
    {
        "group": "Out of Stocks",
        "sku": "CS-HYTE-Y60-B",
        "description": null,
        "eta": null,
        "communicated_date": null,
        "quantity": 0
    },
    {
        "group": "Out of Stocks",
        "sku": "CS-HYTE-Y60-R1-B",
        "description": null,
        "eta": null,
        "communicated_date": null,
        "quantity": 0
    },
    {
        "group": "Out of Stocks",
        "sku": "CS-HYTE-Y70-R1-B",
        "description": null,
        "eta": null,
        "communicated_date": null,
        "quantity": 0
    },
    {
        "group": "Out of Stocks",
        "sku": "CS-HYTE-Y70-R1-BW",
        "description": null,
        "eta": null,
        "communicated_date": null,
        "quantity": 0
    },
    {
        "group": "TBA",
        "sku": "CS-HYTE-Y70TTI-GWING",
        "description": "14.9\" HYTE Y70 TOUCH INFINITE GUNDAM WING",
        "eta": null,
        "communicated_date": "Q4 2025",
        "quantity": 500
    },
    {
        "group": "Out of Stocks",
        "sku": "FAN-HYTE-001",
        "description": null,
        "eta": null,
        "communicated_date": null,
        "quantity": 0
    },
    {
        "group": "Out of Stocks",
        "sku": "FAN-HYTE-FP12-BW-3",
        "description": null,
        "eta": null,
        "communicated_date": null,
        "quantity": 0
    },
    {
        "group": "Out of Stocks",
        "sku": "FAN-HYTE-FP12-BW-3NP",
        "description": null,
        "eta": null,
        "communicated_date": null,
        "quantity": 0
    },
    {
        "group": "TBA",
        "sku": "KEY-HYTE-GWING",
        "description": null,
        "eta": null,
        "communicated_date": "Q4 2025",
        "quantity": 0
    },
    {
        "group": "Out of Stocks",
        "sku": "KEY-HYTE-SUISEI",
        "description": null,
        "eta": null,
        "communicated_date": null,
        "quantity": 0
    },
    {
        "group": "TBA",
        "sku": "MOU-HYTE-GWING",
        "description": null,
        "eta": null,
        "communicated_date": "Q4 2025",
        "quantity": 0
    },
    {
        "group": "Out of Stocks",
        "sku": "MOU-HYTE-P3R-2",
        "description": null,
        "eta": null,
        "communicated_date": null,
        "quantity": 0
    }
]